LICENSE
README.md
pyeventhub/__init__.py
pyeventhub/pyeventhub.py
pyeventhub-0.1.2.dist-info/LICENSE
pyeventhub-0.1.2.dist-info/METADATA
pyeventhub-0.1.2.dist-info/WHEEL
pyeventhub-0.1.2.dist-info/RECORD
